<?xml version="1.0" encoding="ISO-8859-1" standalone="no"?>
<metadata>
	<idinfo>
		<citation>
			<citeinfo>
				<origin>United States. Federal Railroad Administration</origin>
				<pubdate>201103</pubdate>
				<title>Railroad Road Crossings USA 2011</title>
				<geoform>vector digital data</geoform>
				<pubinfo>
					<pubplace>Washington (D.C.)</pubplace>
					<publish>United States. Federal Railroad Administration</publish>
				</pubinfo>
				<onlink>http://www.bts.gov/programs/geographic_information_services/</onlink>
				<lworkcit>
					<citeinfo>
						<origin>United States. Bureau of Transportation Statistics. Office of Geographic Information Services</origin>
						<pubdate>2011</pubdate>
						<title>National Transportation Atlas Database (NTAD) 2011</title>
						<geoform>vector digital data</geoform>
						<pubinfo>
							<pubplace>Washington (D.C.)</pubplace>
							<publish>United States. Bureau of Transportation Statistics. Office of Geographic Information Services</publish>
						</pubinfo>
						<onlink>http://www.bts.gov/programs/geographic_information_services/</onlink>
					</citeinfo>
				</lworkcit>
				<ftname Sync="TRUE">USARailroadCrossings11</ftname>
</citeinfo>
		</citation>
		<descript>
			<abstract>This point dataset represents FRA Grade Crossings in the United States, made from the National Highway-Rail Crossing Inventory Program.  The program is to provide information to Federal, State, and local governments as well as the railroad industry for the improvements of safety at highway-rail crossing.</abstract>
			<purpose>This dataset is intended for researchers, students, and policy makers for reference and mapping purposes, and may be used for basic applications such as viewing, querying, and map output production, or to provide a basemap to support graphical overlays and analysis with other spatial data.</purpose>
			<langdata Sync="TRUE">en</langdata>
</descript>
		<timeperd>
			<timeinfo>
				<sngdate>
					<caldate>2011</caldate>
				</sngdate>
			</timeinfo>
			<current>publication date</current>
		</timeperd>
		<status>
			<progress>In work</progress>
			<update>As needed</update>
		</status>
		<spdom>
			<bounding>
				<westbc>
-158.090675</westbc>
				<eastbc>
-67.097641</eastbc>
				<northbc>
64.919140</northbc>
				<southbc>
20.899705</southbc>
			</bounding>
			<lboundng>
<leftbc Sync="TRUE">-158.090675</leftbc>
<rightbc Sync="TRUE">-67.097641</rightbc>
<bottombc Sync="TRUE">20.899705</bottombc>
<topbc Sync="TRUE">64.919140</topbc>
</lboundng>
</spdom>
		<keywords>
			<theme>
				<themekt>FGDC</themekt>
				<themekey>point</themekey>
			</theme>
			<theme>
				<themekt>ISO 19115 Topic Category</themekt>
				<themekey>transportation</themekey>
			</theme>
			<theme>
				<themekt>LCSH</themekt>
				<themekey>Railroad crossings</themekey>
			</theme>
			<place>
				<placekt>GNS</placekt>
				<placekey>United States</placekey>
			</place>
			<place>
<placekt>LCNH</placekt>
<placekey>Northern Hemipshere</placekey>
<placekey>Western Hemisphere</placekey>
<placekey>North America</placekey>
</place>
</keywords>
		<accconst>Unrestricted Access Online: No restrictions on accessing the data</accconst>
		<useconst>For educational noncommercial use only.</useconst>
		<ptcontac>
			<cntinfo>
				<cntaddr>
					<addrtype>mailing and physical address</addrtype>
					<address>1200 New Jersey Ave S.E.</address>
					<city>Washington</city>
					<state>DC</state>
					<postal>20590</postal>
					<country>USA</country>
				</cntaddr>
				<cntvoice>202.493.6415</cntvoice>
				<cntemail>Raquel.Wright@dot.gov</cntemail>
				<cntperp>
<cntper>Raquel Wright</cntper>
<cntorg>Federal Railroad Administration (FRA)</cntorg>
</cntperp>
</cntinfo>
		</ptcontac>
		<secinfo>
			<secclass>Unclassified</secclass>
		</secinfo>
		<native>Microsoft Windows Vista Version 6.1 (Build 7601) Service Pack 1; ESRI ArcCatalog 9.3.1.4000</native>
		<crossref>
			<citeinfo>
				<origin>Federal Railroad Administration (FRA)</origin>
				<pubdate>2011</pubdate>
				<title>Grade Crossings</title>
				<geoform>vector digital data</geoform>
				<pubinfo>
					<pubplace>Washington, DC</pubplace>
					<publish>Federal Railroad Administration (FRA)</publish>
				</pubinfo>
				<onlink>http://www.bts.gov/programs/geographic_information_services/</onlink>
				<lworkcit>
					<citeinfo>
						<onlink>http://www.bts.gov/programs/geographic_information_services/</onlink>
					</citeinfo>
				</lworkcit>
			</citeinfo>
		</crossref>
		<natvform Sync="TRUE">Shapefile</natvform>
</idinfo>
	<dataqual>
		<attracc>
			<attraccr>The States and railroads maintain their own file and get updated to the FRA.  The information is reported to the FRA on the U.S. DOT-ARR Crossing inventory form.</attraccr>
		</attracc>
		<logic>The quality of the inventory can vary because a record of grade crossing location is being maintained by each state and railroad that is responsible for maintaining its respective information.</logic>
		<posacc>
			<horizpa>
				<horizpar>The spatial quality can vary on who is updating the inventory record.  Quality checks are performed on the spatial file.  A process of applying a county bounding box limit for a particular State and County is applied.  If the location falls outside of the bounding box for the state and county then the record does not get processed into the spatial file.</horizpar>
			</horizpa>
		</posacc>
		<lineage>
			<srcinfo>
				<srccite>
					<citeinfo>
						<origin>Federal Railroad Administration (FRA)</origin>
						<pubdate>2011</pubdate>
						<title>National Highway-Rail Crossing Inventory Program</title>
						<pubinfo>
							<pubplace>Washington, DC</pubplace>
							<publish>Federal Railroad Administration (FRA)</publish>
						</pubinfo>
						<onlink>http://safetydata.fra.dot.gov/officeofsafety/Downloads/Default.asp</onlink>
						<lworkcit>
							<citeinfo>
								<onlink>http://www.bts.gov/programs/geographic_information_services/</onlink>
							</citeinfo>
						</lworkcit>
					</citeinfo>
				</srccite>
				<typesrc>online</typesrc>
				<srctime>
					<timeinfo>
						<sngdate>
							<caldate>2011</caldate>
						</sngdate>
					</timeinfo>
					<srccurr>publication date</srccurr>
				</srctime>
				<srccitea>FRA</srccitea>
				<srccontr>Federal Railroad Administration (FRA)</srccontr>
				<srcscale>Unknown</srcscale>
</srcinfo>
			<procstep>
				<procdesc>The data is downloaded from the HWY-Rail Crossing Inventory Files.  Quality checks are performed on the spatial and attribute data.  The spatial checks were described under the positional Accuracy.  The attribute check will review the consistence of the attributes.</procdesc>
				<srcused>FRA</srcused>
				<procdate>2011</procdate>
				<proccont>
					<cntinfo>
						<cntorgp>
							<cntorg>Federal Railroad Administration (FRA)</cntorg>
						</cntorgp>
					</cntinfo>
				</proccont>
			</procstep>
			<procstep>
<proccont>
<cntinfo>
<cntorgp>
<cntorg>Tufts University GIS Center</cntorg>
</cntorgp>
<cntpos>Data Technician</cntpos>
</cntinfo>
</proccont>
<procdesc>In order to meet Tufts University's metadata standards:
&amp;gt;Changed name of file from "rr_crossings" to "USARailroadCrossings11"
&amp;gt;Changed citatition title from "Rail Road Roadway Crossings" to "Railroad Road Crossings USA 2011"
&amp;gt;Changed access contraints from "No restrictions on accessing the data" to "Unrestricted Access Online: No restrictions on accessing the data"
&amp;gt;Changed originator/publisher from "Federal Railroad Administration (FRA)" to "United States. Federal Railroad Administration"
&amp;gt;Changed publication place to reflect LCNH formatting
&amp;gt;Changed publication date from "March 2011" to "201103"
&amp;gt;Added theme keyword "point" to added theme keyword thesaurus "FGDC"
&amp;gt;Added ISO 19115 Topic Category keyword
&amp;gt;Added LCSH theme keyword
&amp;gt;Added to Larger work Citation originator, pubdate, title, pubplace, publisher
&amp;gt;Added GNS place keywords
&amp;gt;Replaced Tufts as the distributor
&amp;gt;Exported metadata</procdesc>
<procdate>20111201</procdate>
</procstep>
</lineage>
	</dataqual>
	<spdoinfo>
		<direct>Vector</direct>
		<ptvctinf>
			<sdtsterm Name="USARailroadCrossings11">
				<sdtstype>Entity point</sdtstype>
				<ptvctcnt>248845</ptvctcnt>
			</sdtsterm>
			<esriterm Name="USARailroadCrossings11">
<efeatyp Sync="TRUE">Simple</efeatyp>
<efeageom Sync="TRUE">Point</efeageom>
<esritopo Sync="TRUE">FALSE</esritopo>
<efeacnt Sync="TRUE">248845</efeacnt>
<spindex Sync="TRUE">TRUE</spindex>
<linrefer Sync="TRUE">FALSE</linrefer>
</esriterm>
</ptvctinf>
	</spdoinfo>
	<spref>
		<horizsys>
			<geograph>
				<latres>0.000000</latres>
				<longres>0.000000</longres>
				<geogunit>Decimal degrees</geogunit>
			</geograph>
			<geodetic>
				<horizdn>D_WGS_1984</horizdn>
				<ellips>WGS_1984</ellips>
				<semiaxis>6378137.000000</semiaxis>
				<denflat>298.257224</denflat>
			</geodetic>
			<cordsysn>
<geogcsn Sync="TRUE">GCS_WGS_1984</geogcsn>
</cordsysn>
</horizsys>
	</spref>
	<eainfo>
		<detailed Name="USARailroadCrossings11">
			<enttyp>
				<enttypl>
USArailroadCrossings11</enttypl>
				<enttypd>Highway-rail grade crossing means a location where a public highway, road, street, or private roadway, including associated sidewalks and pathways, crosses one or more railroad tracks at grade.</enttypd>
				<enttypds>FRA</enttypds>
				<enttypt Sync="TRUE">Feature Class</enttypt>
<enttypc Sync="TRUE">248845</enttypc>
</enttyp>
			<attr>
				<attrlabl>FID</attrlabl>
				<attrdef>Internal feature number</attrdef>
				<attrdefs>Environmental Systems Research Institute (Redlands, Calif.)</attrdefs>
				<attrdomv>
					<udom>Sequential unique whole numbers that are automatically generated.</udom>
				</attrdomv>
				<attalias Sync="TRUE">FID</attalias>
<attrtype Sync="TRUE">OID</attrtype>
<attwidth Sync="TRUE">4</attwidth>
<atprecis Sync="TRUE">0</atprecis>
<attscale Sync="TRUE">0</attscale>
</attr>
			<attr>
				<attrlabl>Shape</attrlabl>
				<attrdef>Feature geometry</attrdef>
				<attrdefs>Environmental Systems Research Institute (Redlands, Calif.)</attrdefs>
				<attrdomv>
					<udom>Coordinates defining the features.</udom>
				</attrdomv>
				<attalias Sync="TRUE">Shape</attalias>
<attrtype Sync="TRUE">Geometry</attrtype>
<attwidth Sync="TRUE">0</attwidth>
<atprecis Sync="TRUE">0</atprecis>
<attscale Sync="TRUE">0</attscale>
</attr>
			<attr>
				<attrlabl>CROSSING</attrlabl>
				<attrdef>US DOT Valid Crossing ID Number</attrdef>
				<attrdefs>Tufts University. Geographic Information Systems Center</attrdefs>
				<attrdomv>
					<codesetd>
						<codesetn>Character value</codesetn>
						<codesets>FRA</codesets>
					</codesetd>
				</attrdomv>
				<attalias Sync="TRUE">CROSSING</attalias>
<attrtype Sync="TRUE">String</attrtype>
<attwidth Sync="TRUE">7</attwidth>
</attr>
			<attr>
				<attrlabl>RAILROAD</attrlabl>
				<attrdef>The reporting mark of the 1st owning railroad. A mark of 'XXXX' indicates an abandoned link. Rule 260 codes are used where available. A mark of 'DUMX' indicates an added connecting link.</attrdef>
				<attrdefs>Tufts University. Geographic Information Systems Center</attrdefs>
				<attrdomv>
					<codesetd>
						<codesetn>FRA Rule 260 and Owner Codes</codesetn>
						<codesets>FRA</codesets>
					</codesetd>
				</attrdomv>
				<attalias Sync="TRUE">RAILROAD</attalias>
<attrtype Sync="TRUE">String</attrtype>
<attwidth Sync="TRUE">4</attwidth>
</attr>
			<attr>
				<attrlabl>RRDIV</attrlabl>
				<attrdef>Railroad Division Name or Blank</attrdef>
				<attrdefs>Tufts University. Geographic Information Systems Center</attrdefs>
				<attrdomv>
					<codesetd>
						<codesetn>Character value</codesetn>
						<codesets>FRA</codesets>
					</codesetd>
				</attrdomv>
				<attalias Sync="TRUE">RRDIV</attalias>
<attrtype Sync="TRUE">String</attrtype>
<attwidth Sync="TRUE">14</attwidth>
</attr>
			<attr>
				<attrlabl>RRSUBDIV</attrlabl>
				<attrdef>Railroad Subdivision or Blank</attrdef>
				<attrdefs>Tufts University. Geographic Information Systems Center</attrdefs>
				<attrdomv>
					<codesetd>
						<codesetn>Character value</codesetn>
						<codesets>FRA</codesets>
					</codesetd>
				</attrdomv>
				<attalias Sync="TRUE">RRSUBDIV</attalias>
<attrtype Sync="TRUE">String</attrtype>
<attwidth Sync="TRUE">14</attwidth>
</attr>
			<attr>
				<attrlabl>HIGHWAY</attrlabl>
				<attrdef>Highway Type and Number</attrdef>
				<attrdefs>Tufts University. Geographic Information Systems Center</attrdefs>
				<attrdomv>
					<codesetd>
						<codesetn>Character value</codesetn>
						<codesets>FRA</codesets>
					</codesetd>
				</attrdomv>
				<attalias Sync="TRUE">HIGHWAY</attalias>
<attrtype Sync="TRUE">String</attrtype>
<attwidth Sync="TRUE">7</attwidth>
</attr>
			<attr>
				<attrlabl>STREET</attrlabl>
				<attrdef>Street or Road Name</attrdef>
				<attrdefs>Tufts University. Geographic Information Systems Center</attrdefs>
				<attrdomv>
					<codesetd>
						<codesetn>Character value</codesetn>
						<codesets>FRA</codesets>
					</codesetd>
				</attrdomv>
				<attalias Sync="TRUE">STREET</attalias>
<attrtype Sync="TRUE">String</attrtype>
<attwidth Sync="TRUE">17</attwidth>
</attr>
			<attr>
				<attrlabl>TYPEXING</attrlabl>
				<attrdef>Type of Crossing</attrdef>
				<attrdefs>Tufts University. Geographic Information Systems Center</attrdefs>
				<attrdomv>
					<edom>
						<edomv>11</edomv>
						<edomvd>Pedestrain at grade</edomvd>
						<edomvds>Tufts University. Geographic Information Systems Center</edomvds>
					</edom>
				</attrdomv>
				<attrdomv>
					<edom>
						<edomv>12</edomv>
						<edomvd>Pedestrain RR under</edomvd>
						<edomvds>Tufts University. Geographic Information Systems Center</edomvds>
					</edom>
				</attrdomv>
				<attrdomv>
					<edom>
						<edomv>13</edomv>
						<edomvd>Pedestrain RR over</edomvd>
						<edomvds>Tufts University. Geographic Information Systems Center</edomvds>
					</edom>
				</attrdomv>
				<attrdomv>
					<edom>
						<edomv>21</edomv>
						<edomvd>Private at grade</edomvd>
						<edomvds>Tufts University. Geographic Information Systems Center</edomvds>
					</edom>
				</attrdomv>
				<attrdomv>
					<edom>
						<edomv>22</edomv>
						<edomvd>Private RR under</edomvd>
						<edomvds>Tufts University. Geographic Information Systems Center</edomvds>
					</edom>
				</attrdomv>
				<attrdomv>
					<edom>
						<edomv>23</edomv>
						<edomvd>Private RR over</edomvd>
						<edomvds>Tufts University. Geographic Information Systems Center</edomvds>
					</edom>
				</attrdomv>
				<attrdomv>
					<edom>
						<edomv>31</edomv>
						<edomvd>Public at grade</edomvd>
						<edomvds>Tufts University. Geographic Information Systems Center</edomvds>
					</edom>
				</attrdomv>
				<attrdomv>
					<edom>
						<edomv>32</edomv>
						<edomvd>Public RR under</edomvd>
						<edomvds>Tufts University. Geographic Information Systems Center</edomvds>
					</edom>
				</attrdomv>
				<attrdomv>
					<edom>
						<edomv>33</edomv>
						<edomvd>Public RR over</edomvd>
						<edomvds>Tufts University. Geographic Information Systems Center</edomvds>
					</edom>
				</attrdomv>
				<attalias Sync="TRUE">TYPEXING</attalias>
<attrtype Sync="TRUE">String</attrtype>
<attwidth Sync="TRUE">1</attwidth>
</attr>
			<attr>
				<attrlabl>POSXING</attrlabl>
				<attrdef>Position of Crossing</attrdef>
				<attrdefs>Tufts University. Geographic Information Systems Center</attrdefs>
				<attrdomv>
					<edom>
						<edomv>1</edomv>
						<edomvd>At grade under</edomvd>
						<edomvds>Tufts University. Geographic Information Systems Center</edomvds>
					</edom>
				</attrdomv>
				<attrdomv>
					<edom>
						<edomv>2</edomv>
						<edomvd>RR Under</edomvd>
						<edomvds>Tufts University. Geographic Information Systems Center</edomvds>
					</edom>
				</attrdomv>
				<attrdomv>
					<edom>
						<edomv>3</edomv>
						<edomvd>RR over</edomvd>
						<edomvds>Tufts University. Geographic Information Systems Center</edomvds>
					</edom>
				</attrdomv>
				<attalias Sync="TRUE">POSXING</attalias>
<attrtype Sync="TRUE">String</attrtype>
<attwidth Sync="TRUE">1</attwidth>
</attr>
			<attr>
				<attrlabl>STFIPS</attrlabl>
				<attrdef>Federal Information Processing Standard (FIPS) State Code</attrdef>
				<attrdefs>National Institute of Standards and Technology (U.S.)</attrdefs>
				<attrdomv>
					<codesetd>
						<codesetn>Character value</codesetn>
						<codesets>FRA</codesets>
					</codesetd>
				</attrdomv>
				<attalias Sync="TRUE">STFIPS</attalias>
<attrtype Sync="TRUE">String</attrtype>
<attwidth Sync="TRUE">2</attwidth>
</attr>
			<attr>
				<attrlabl>CTFIPS</attrlabl>
				<attrdef>Federal Information Processing Standard (FIPS) County Code</attrdef>
				<attrdefs>National Institute of Standards and Technology (U.S.)</attrdefs>
				<attrdomv>
					<codesetd>
						<codesetn>Character value</codesetn>
						<codesets>FRA</codesets>
					</codesetd>
				</attrdomv>
				<attalias Sync="TRUE">CTFIPS</attalias>
<attrtype Sync="TRUE">String</attrtype>
<attwidth Sync="TRUE">5</attwidth>
</attr>
			<attr>
				<attrlabl>COUNTY</attrlabl>
				<attrdef>Name of County</attrdef>
				<attrdefs>National Institute of Standards and Technology (U.S.)</attrdefs>
				<attrdomv>
					<codesetd>
						<codesetn>Character value</codesetn>
						<codesets>FRA</codesets>
					</codesetd>
				</attrdomv>
				<attalias Sync="TRUE">COUNTY</attalias>
<attrtype Sync="TRUE">String</attrtype>
<attwidth Sync="TRUE">66</attwidth>
</attr>
			<attr>
				<attrlabl>State_ABBR</attrlabl>
				<attrdef>State Abbreviation</attrdef>
				<attrdefs>Tufts University. Geographic Information Systems Center</attrdefs>
				<attrdomv>
					<codesetd>
						<codesetn>Abbreviation of States</codesetn>
						<codesets>FRA</codesets>
					</codesetd>
				</attrdomv>
				<attalias Sync="TRUE">State_ABBR</attalias>
<attrtype Sync="TRUE">String</attrtype>
<attwidth Sync="TRUE">2</attwidth>
</attr>
			<attr>
				<attrlabl>TYPE</attrlabl>
				<attrdef>Public or Private Crossing</attrdef>
				<attrdefs>Tufts University. Geographic Information Systems Center</attrdefs>
				<attrdomv>
					<edom>
						<edomv>PU</edomv>
						<edomvd>Public</edomvd>
						<edomvds>Tufts University. Geographic Information Systems Center</edomvds>
					</edom>
				</attrdomv>
				<attrdomv>
					<edom>
						<edomv>PR</edomv>
						<edomvd>Private</edomvd>
						<edomvds>Tufts University. Geographic Information Systems Center</edomvds>
					</edom>
				</attrdomv>
				<attalias Sync="TRUE">TYPE</attalias>
<attrtype Sync="TRUE">String</attrtype>
<attwidth Sync="TRUE">2</attwidth>
</attr>
			<attr>
				<attrlabl>VERSION</attrlabl>
				<attrdef>The VERSION is a 2-digit number that will be incremented for all records in the database whenever a new release is distributed.</attrdef>
				<attrdefs>United States. Dept. of Transportation. Research and Innovative Technology Administration</attrdefs>
				<attrdomv>
					<rdom>
						<rdommin>00</rdommin>
						<rdommax>99</rdommax>
					</rdom>
				</attrdomv>
				<attalias Sync="TRUE">VERSION</attalias>
<attrtype Sync="TRUE">String</attrtype>
<attwidth Sync="TRUE">2</attwidth>
</attr>
		</detailed>
		<overview>
		</overview>
	</eainfo>
	<distinfo>
		<distrib>
			<cntinfo>
				<cntorgp>
					<cntorg>Tufts University GIS Center</cntorg>
				</cntorgp>
				<cntpos>Data Technician</cntpos>
				<cntaddr>
					<addrtype>mailing and physical address</addrtype>
					<address>Academic Technology</address>
					<address>16 Dearborn Rd</address>
					<city>Somerville</city>
					<state>MA</state>
					<postal>02144</postal>
					<country>USA</country>
				</cntaddr>
				<cntvoice>617-627-3380</cntvoice>
				<cntemail>gis-support@elist.tufts.edu</cntemail>
				<hours>Monday - Friday, 9:00 am - 5:00 pm EST-USA</hours>
			</cntinfo>
		</distrib>
		<resdesc>Online Dataset</resdesc>
		<distliab>Although this data is being distributed by Tufts University, no warranty expressed or implied is made by the University as to the accuracy of the data and related materials. The act of distribution shall not constitute any such warranty, and no responsibility is assumed by the University in the use of this data, or related materials.</distliab>
		<stdorder>
			<digform>
				<digtinfo>
					<transize>5.950</transize>
					<dssize Sync="TRUE">6.645</dssize>
</digtinfo>
			</digform>
		</stdorder>
	</distinfo>
	<metainfo>
		<metd>20111201</metd>
		<metc>
			<cntinfo>
				<cntorgp>
					<cntorg>Tufts University GIS Center</cntorg>
				</cntorgp>
				<cntaddr>
					<addrtype>mailing and physical address</addrtype>
					<address>Academic Technology</address>
					<city>Somerville</city>
					<state>MA</state>
					<postal>02144</postal>
					<country>USA</country>
					<address>16 Dearborn Ave</address>
</cntaddr>
				<cntvoice>617-627-3380</cntvoice>
				<cntpos>GIS Data Technician</cntpos>
<cntemail>gis-support@elist.tufts.edu</cntemail>
<hours>Monday-Friday, 9:00 AM-5:00 PM, EST-USA</hours>
</cntinfo>
		</metc>
		<metstdn>FGDC Content Standards for Digital Geospatial Metadata</metstdn>
		<metstdv>FGDC-STD-001-1998</metstdv>
		<mettc>local time</mettc>
		<metextns>
			<onlink>http://www.esri.com/metadata/esriprof80.html</onlink>
			<metprof>ESRI Metadata Profile</metprof>
		</metextns>
		<langmeta Sync="TRUE">en</langmeta>
<metextns>
<onlink Sync="TRUE">http://www.esri.com/metadata/esriprof80.html</onlink>
<metprof Sync="TRUE">ESRI Metadata Profile</metprof>
</metextns>
</metainfo>
	<dataIdInfo>
<envirDesc Sync="TRUE">Microsoft Windows Vista Version 6.1 (Build 7601) Service Pack 1; ESRI ArcCatalog 9.3.1.4000</envirDesc>
<dataLang>
<languageCode Sync="TRUE" value="en"/>
</dataLang>
<idCitation>
<resTitle Sync="TRUE">USARailroadCrossings11</resTitle>
<presForm>
<PresFormCd Sync="TRUE" value="005"/>
</presForm>
</idCitation>
<spatRpType>
<SpatRepTypCd Sync="TRUE" value="001"/>
</spatRpType>
<dataExt>
<geoEle>
<GeoBndBox esriExtentType="native">
<westBL Sync="TRUE">-158.090675</westBL>
<eastBL Sync="TRUE">-67.097641</eastBL>
<northBL Sync="TRUE">64.91914</northBL>
<southBL Sync="TRUE">20.899705</southBL>
<exTypeCode Sync="TRUE">1</exTypeCode>
</GeoBndBox>
</geoEle>
</dataExt>
<geoBox esriExtentType="decdegrees">
<westBL Sync="TRUE">-158.090675</westBL>
<eastBL Sync="TRUE">-67.097641</eastBL>
<northBL Sync="TRUE">64.91914</northBL>
<southBL Sync="TRUE">20.899705</southBL>
<exTypeCode Sync="TRUE">1</exTypeCode>
</geoBox>
</dataIdInfo>
<mdLang>
<languageCode Sync="TRUE" value="en"/>
</mdLang>
<mdStanName Sync="TRUE">ISO 19115 Geographic Information - Metadata</mdStanName>
<mdStanVer Sync="TRUE">DIS_ESRI1.0</mdStanVer>
<mdChar>
<CharSetCd Sync="TRUE" value="004"/>
</mdChar>
<mdHrLv>
<ScopeCd Sync="TRUE" value="005"/>
</mdHrLv>
<mdHrLvName Sync="TRUE">dataset</mdHrLvName>
<distInfo>
<distributor>
<distorTran>
<onLineSrc>
<orDesc Sync="TRUE">002</orDesc>
<linkage Sync="TRUE">file://\\rstore2\gisprojects$\GIS_Center_Projects\EnterpriseGIS\Layers\RITA\USARailroadCrossings11.shp</linkage>
<protocol Sync="TRUE">Local Area Network</protocol>
</onLineSrc>
<transSize Sync="TRUE">6.645</transSize>
</distorTran>
<distorFormat>
<formatName Sync="TRUE">Shapefile</formatName>
</distorFormat>
</distributor>
</distInfo>
<refSysInfo>
<RefSystem>
<refSysID>
<identCode Sync="TRUE">GCS_WGS_1984</identCode>
</refSysID>
</RefSystem>
</refSysInfo>
<spatRepInfo>
<VectSpatRep>
<topLvl>
<TopoLevCd Sync="TRUE" value="001"/>
</topLvl>
<geometObjs Name="USARailroadCrossings11">
<geoObjTyp>
<GeoObjTypCd Sync="TRUE" value="004"/>
</geoObjTyp>
<geoObjCnt Sync="TRUE">248845</geoObjCnt>
</geometObjs>
</VectSpatRep>
</spatRepInfo>
<Esri>
<SyncDate>20140514</SyncDate>
<SyncTime>11445600</SyncTime>
<ModDate>20140514</ModDate>
<ModTime>11445600</ModTime>
</Esri>
<mdDateSt Sync="TRUE">20140514</mdDateSt>
</metadata>
